matlab2cpp/__init__.py
matlab2cpp/__main__.py
matlab2cpp/collection.py
matlab2cpp/datatype.py
matlab2cpp/frontend.py
matlab2cpp/m2cpp.py
matlab2cpp/matlab_types.py
matlab2cpp/modify.py
matlab2cpp/mwhos.py
matlab2cpp/mwrapmat.py
matlab2cpp/parser.py
matlab2cpp/pyplot.py
matlab2cpp/qfunctions.py
matlab2cpp/setpaths.py
matlab2cpp/configure/__init__.py
matlab2cpp/configure/armadillo.py
matlab2cpp/configure/backends.py
matlab2cpp/configure/datatypes.py
matlab2cpp/configure/frontend.py
matlab2cpp/configure/funcs.py
matlab2cpp/configure/reserved.py
matlab2cpp/manual/__init__.py
matlab2cpp/manual/usr00_introduction.py
matlab2cpp/manual/usr01_interaction.py
matlab2cpp/manual/usr02_datatype.py
matlab2cpp/manual/usr03_rules.py
matlab2cpp/manual/usr04_node.py
matlab2cpp/manual/usr05_installation.py
matlab2cpp/node/__init__.py
matlab2cpp/node/backend.py
matlab2cpp/node/frontend.py
matlab2cpp/node/m2cpp.py
matlab2cpp/node/reference.py
matlab2cpp/rules/__init__.py
matlab2cpp/rules/_cell.py
matlab2cpp/rules/_char.py
matlab2cpp/rules/_code_block.py
matlab2cpp/rules/_cube.py
matlab2cpp/rules/_cx_cube.py
matlab2cpp/rules/_cx_double.py
matlab2cpp/rules/_cx_mat.py
matlab2cpp/rules/_cx_rowvec.py
matlab2cpp/rules/_cx_vec.py
matlab2cpp/rules/_double.py
matlab2cpp/rules/_expression.py
matlab2cpp/rules/_fcube.py
matlab2cpp/rules/_float.py
matlab2cpp/rules/_fmat.py
matlab2cpp/rules/_frowvec.py
matlab2cpp/rules/_func_lambda.py
matlab2cpp/rules/_func_return.py
matlab2cpp/rules/_func_returns.py
matlab2cpp/rules/_fvec.py
matlab2cpp/rules/_icube.py
matlab2cpp/rules/_imat.py
matlab2cpp/rules/_int.py
matlab2cpp/rules/_irowvec.py
matlab2cpp/rules/_ivec.py
matlab2cpp/rules/_mat.py
matlab2cpp/rules/_matrix.py
matlab2cpp/rules/_program.py
matlab2cpp/rules/_reserved.py
matlab2cpp/rules/_rowvec.py
matlab2cpp/rules/_size_t.py
matlab2cpp/rules/_string.py
matlab2cpp/rules/_struct.py
matlab2cpp/rules/_structs.py
matlab2cpp/rules/_ucube.py
matlab2cpp-2.0.1.dist-info/DESCRIPTION.rst
matlab2cpp-2.0.1.dist-info/METADATA
matlab2cpp-2.0.1.dist-info/RECORD
matlab2cpp-2.0.1.dist-info/WHEEL
matlab2cpp-2.0.1.dist-info/entry_points.txt
matlab2cpp-2.0.1.dist-info/metadata.json
matlab2cpp-2.0.1.dist-info/top_level.txt
