Metadata-Version: 2.0
Name: matlab2cpp
Version: 2.0.1
Summary: Matlab to C++ transpiler
Home-page: http://github.com/jonathf/matlab2cpp
Author: Jonathan Feinberg
Author-email: jonathan@feinberg.no
License: BSD
Platform: UNKNOWN
Classifier: Development Status :: 4 - Beta
Classifier: Environment :: Console
Classifier: Intended Audience :: Developers
Classifier: License :: OSI Approved :: BSD License
Classifier: Operating System :: OS Independent
Classifier: Natural Language :: English
Classifier: Programming Language :: Python
Classifier: Topic :: Software Development :: Compilers
